{
  "_format": "hh-sol-cache-2",
  "files": {
    "/workspace/Blockchain/Project/contracts/AssetRegistry.sol": {
      "lastModificationDate": 1782801035878,
      "contentHash": "8c71afeeafb3f7626f8111fad135701e",
      "sourceName": "contracts/AssetRegistry.sol",
      "solcConfig": {
        "version": "0.8.28",
        "settings": {
          "optimizer": {
            "enabled": true,
            "runs": 200
          },
          "viaIR": true,
          "evmVersion": "paris",
          "outputSelection": {
            "*": {
              "*": [
                "abi",
                "evm.bytecode",
                "evm.deployedBytecode",
                "evm.methodIdentifiers",
                "metadata"
              ],
              "": [
                "ast"
              ]
            }
          }
        }
      },
      "imports": [],
      "versionPragmas": [
        "^0.8.28"
      ],
      "artifacts": [
        "AssetRegistry"
      ]
    },
    "/workspace/Blockchain/Project/contracts/Compliance.sol": {
      "lastModificationDate": 1782800053852,
      "contentHash": "d9c54c8e4b993d91fa8cf7a70770fb87",
      "sourceName": "contracts/Compliance.sol",
      "solcConfig": {
        "version": "0.8.28",
        "settings": {
          "optimizer": {
            "enabled": true,
            "runs": 200
          },
          "viaIR": true,
          "evmVersion": "paris",
          "outputSelection": {
            "*": {
              "*": [
                "abi",
                "evm.bytecode",
                "evm.deployedBytecode",
                "evm.methodIdentifiers",
                "metadata"
              ],
              "": [
                "ast"
              ]
            }
          }
        }
      },
      "imports": [],
      "versionPragmas": [
        "^0.8.28"
      ],
      "artifacts": [
        "Compliance"
      ]
    },
    "/workspace/Blockchain/Project/contracts/DutchAuction.sol": {
      "lastModificationDate": 1782799991556,
      "contentHash": "ef758d074b30773ef364cfb533a70c15",
      "sourceName": "contracts/DutchAuction.sol",
      "solcConfig": {
        "version": "0.8.28",
        "settings": {
          "optimizer": {
            "enabled": true,
            "runs": 200
          },
          "viaIR": true,
          "evmVersion": "paris",
          "outputSelection": {
            "*": {
              "*": [
                "abi",
                "evm.bytecode",
                "evm.deployedBytecode",
                "evm.methodIdentifiers",
                "metadata"
              ],
              "": [
                "ast"
              ]
            }
          }
        }
      },
      "imports": [],
      "versionPragmas": [
        "^0.8.28"
      ],
      "artifacts": [
        "DutchAuction"
      ]
    },
    "/workspace/Blockchain/Project/contracts/Insurance.sol": {
      "lastModificationDate": 1782801281224,
      "contentHash": "e3614fb0bfa780ae2ab01ac50e5c7ac0",
      "sourceName": "contracts/Insurance.sol",
      "solcConfig": {
        "version": "0.8.28",
        "settings": {
          "optimizer": {
            "enabled": true,
            "runs": 200
          },
          "viaIR": true,
          "evmVersion": "paris",
          "outputSelection": {
            "*": {
              "*": [
                "abi",
                "evm.bytecode",
                "evm.deployedBytecode",
                "evm.methodIdentifiers",
                "metadata"
              ],
              "": [
                "ast"
              ]
            }
          }
        }
      },
      "imports": [],
      "versionPragmas": [
        "^0.8.28"
      ],
      "artifacts": [
        "Insurance"
      ]
    },
    "/workspace/Blockchain/Project/contracts/LegalEnforcement.sol": {
      "lastModificationDate": 1782799941974,
      "contentHash": "69b1212a90f6ed585eba655df24cd632",
      "sourceName": "contracts/LegalEnforcement.sol",
      "solcConfig": {
        "version": "0.8.28",
        "settings": {
          "optimizer": {
            "enabled": true,
            "runs": 200
          },
          "viaIR": true,
          "evmVersion": "paris",
          "outputSelection": {
            "*": {
              "*": [
                "abi",
                "evm.bytecode",
                "evm.deployedBytecode",
                "evm.methodIdentifiers",
                "metadata"
              ],
              "": [
                "ast"
              ]
            }
          }
        }
      },
      "imports": [],
      "versionPragmas": [
        "^0.8.28"
      ],
      "artifacts": [
        "LegalEnforcement"
      ]
    },
    "/workspace/Blockchain/Project/contracts/Marketplace.sol": {
      "lastModificationDate": 1782821969922,
      "contentHash": "ea2a4527cf7d405ff06e0d5677a65c5f",
      "sourceName": "contracts/Marketplace.sol",
      "solcConfig": {
        "version": "0.8.28",
        "settings": {
          "optimizer": {
            "enabled": true,
            "runs": 200
          },
          "viaIR": true,
          "evmVersion": "paris",
          "outputSelection": {
            "*": {
              "*": [
                "abi",
                "evm.bytecode",
                "evm.deployedBytecode",
                "evm.methodIdentifiers",
                "metadata"
              ],
              "": [
                "ast"
              ]
            }
          }
        }
      },
      "imports": [],
      "versionPragmas": [
        "^0.8.28"
      ],
      "artifacts": [
        "Marketplace"
      ]
    },
    "/workspace/Blockchain/Project/contracts/RWAToken.sol": {
      "lastModificationDate": 1782203278126,
      "contentHash": "aa9e2d9ff71909c55fec7b0166cb767b",
      "sourceName": "contracts/RWAToken.sol",
      "solcConfig": {
        "version": "0.8.28",
        "settings": {
          "optimizer": {
            "enabled": true,
            "runs": 200
          },
          "viaIR": true,
          "evmVersion": "paris",
          "outputSelection": {
            "*": {
              "*": [
                "abi",
                "evm.bytecode",
                "evm.deployedBytecode",
                "evm.methodIdentifiers",
                "metadata"
              ],
              "": [
                "ast"
              ]
            }
          }
        }
      },
      "imports": [],
      "versionPragmas": [
        "^0.8.28"
      ],
      "artifacts": [
        "RWAToken"
      ]
    },
    "/workspace/Blockchain/Project/contracts/RevenueDistributor.sol": {
      "lastModificationDate": 1782800124219,
      "contentHash": "d99cbfcd788c0cb69edafe721b297b7e",
      "sourceName": "contracts/RevenueDistributor.sol",
      "solcConfig": {
        "version": "0.8.28",
        "settings": {
          "optimizer": {
            "enabled": true,
            "runs": 200
          },
          "viaIR": true,
          "evmVersion": "paris",
          "outputSelection": {
            "*": {
              "*": [
                "abi",
                "evm.bytecode",
                "evm.deployedBytecode",
                "evm.methodIdentifiers",
                "metadata"
              ],
              "": [
                "ast"
              ]
            }
          }
        }
      },
      "imports": [],
      "versionPragmas": [
        "^0.8.28"
      ],
      "artifacts": [
        "RevenueDistributor"
      ]
    },
    "/workspace/Blockchain/Project/contracts/RiskManager.sol": {
      "lastModificationDate": 1782800150669,
      "contentHash": "b990f2c91e414a07d5e73ac42d449b74",
      "sourceName": "contracts/RiskManager.sol",
      "solcConfig": {
        "version": "0.8.28",
        "settings": {
          "optimizer": {
            "enabled": true,
            "runs": 200
          },
          "viaIR": true,
          "evmVersion": "paris",
          "outputSelection": {
            "*": {
              "*": [
                "abi",
                "evm.bytecode",
                "evm.deployedBytecode",
                "evm.methodIdentifiers",
                "metadata"
              ],
              "": [
                "ast"
              ]
            }
          }
        }
      },
      "imports": [],
      "versionPragmas": [
        "^0.8.28"
      ],
      "artifacts": [
        "RiskManager"
      ]
    },
    "/workspace/Blockchain/Project/contracts/Valuation.sol": {
      "lastModificationDate": 1782826317315,
      "contentHash": "aae1eed99faffb883152529828ba6fa5",
      "sourceName": "contracts/Valuation.sol",
      "solcConfig": {
        "version": "0.8.28",
        "settings": {
          "optimizer": {
            "enabled": true,
            "runs": 200
          },
          "viaIR": true,
          "evmVersion": "paris",
          "outputSelection": {
            "*": {
              "*": [
                "abi",
                "evm.bytecode",
                "evm.deployedBytecode",
                "evm.methodIdentifiers",
                "metadata"
              ],
              "": [
                "ast"
              ]
            }
          }
        }
      },
      "imports": [],
      "versionPragmas": [
        "^0.8.28"
      ],
      "artifacts": [
        "Valuation"
      ]
    }
  }
}
